radarr/__init__.py
radarr/api_client.py
radarr/api_response.py
radarr/configuration.py
radarr/exceptions.py
radarr/py.typed
radarr/rest.py
radarr/api/__init__.py
radarr/api/alternative_title_api.py
radarr/api/api_info_api.py
radarr/api/authentication_api.py
radarr/api/auto_tagging_api.py
radarr/api/backup_api.py
radarr/api/blocklist_api.py
radarr/api/calendar_api.py
radarr/api/calendar_feed_api.py
radarr/api/collection_api.py
radarr/api/command_api.py
radarr/api/credit_api.py
radarr/api/custom_filter_api.py
radarr/api/custom_format_api.py
radarr/api/cutoff_api.py
radarr/api/delay_profile_api.py
radarr/api/disk_space_api.py
radarr/api/download_client_api.py
radarr/api/download_client_config_api.py
radarr/api/extra_file_api.py
radarr/api/file_system_api.py
radarr/api/health_api.py
radarr/api/history_api.py
radarr/api/host_config_api.py
radarr/api/import_list_api.py
radarr/api/import_list_config_api.py
radarr/api/import_list_exclusion_api.py
radarr/api/import_list_movies_api.py
radarr/api/indexer_api.py
radarr/api/indexer_config_api.py
radarr/api/indexer_flag_api.py
radarr/api/language_api.py
radarr/api/localization_api.py
radarr/api/log_api.py
radarr/api/log_file_api.py
radarr/api/manual_import_api.py
radarr/api/media_cover_api.py
radarr/api/media_management_config_api.py
radarr/api/metadata_api.py
radarr/api/metadata_config_api.py
radarr/api/missing_api.py
radarr/api/movie_api.py
radarr/api/movie_editor_api.py
radarr/api/movie_file_api.py
radarr/api/movie_folder_api.py
radarr/api/movie_import_api.py
radarr/api/movie_lookup_api.py
radarr/api/naming_config_api.py
radarr/api/notification_api.py
radarr/api/parse_api.py
radarr/api/ping_api.py
radarr/api/quality_definition_api.py
radarr/api/quality_profile_api.py
radarr/api/quality_profile_schema_api.py
radarr/api/queue_action_api.py
radarr/api/queue_api.py
radarr/api/queue_details_api.py
radarr/api/queue_status_api.py
radarr/api/release_api.py
radarr/api/release_profile_api.py
radarr/api/release_push_api.py
radarr-1.2.1.dist-info/licenses/LICENSE
radarr-1.2.1.dist-info/METADATA
radarr-1.2.1.dist-info/WHEEL
radarr-1.2.1.dist-info/top_level.txt
radarr-1.2.1.dist-info/RECORD
